LICENSE
MANIFEST.in
README.md
setup.py
./.gitlab-ci.yml
./pyPhasesRecordloaderAlice/config.yaml
pyPhasesRecordloaderAlice/Plugin.py
pyPhasesRecordloaderAlice/__init__.py
pyPhasesRecordloaderAlice/config.yaml
pyPhasesRecordloaderAlice.egg-info/PKG-INFO
pyPhasesRecordloaderAlice.egg-info/SOURCES.txt
pyPhasesRecordloaderAlice.egg-info/dependency_links.txt
pyPhasesRecordloaderAlice.egg-info/requires.txt
pyPhasesRecordloaderAlice.egg-info/top_level.txt
pyPhasesRecordloaderAlice/recordLoaders/AliceRMLLoader.py
pyPhasesRecordloaderAlice/recordLoaders/AliceTextReportLoader.py
pyPhasesRecordloaderAlice/recordLoaders/RecordLoaderAlice.py
pyPhasesRecordloaderAlice/recordLoaders/__init__.py